proyecto_I2S/src/i2s/i2s_tx.v
module i2s_tx (
    input wire clk, rst,
    input wire [15:0] fifo_out,
    input wire fifo_empty,
    output reg rd_en,
    output reg bclk, 
    output wire din, 
    output wire lrc
);

    localparam LIMIT = 18; 

    reg [7:0] tick;
    reg strobe;
    reg [4:0] cnt_lrc;
    reg [15:0] sreg;

    always @(posedge clk) begin
        if (rst) begin 
            tick <= 0; 
            bclk <= 0; 
            strobe <= 0; 
        end else begin
            strobe <= 0;
            if (tick >= LIMIT-1) begin
                tick <= 0;
                bclk <= ~bclk; 
                if (bclk == 1) strobe <= 1; 
            end else begin
                tick <= tick + 1;
            end
        end
    end

    always @(posedge clk) begin
        if (rst) begin
            cnt_lrc <= 0;
            rd_en <= 0;
            sreg <= 0;
        end else if (strobe) begin
            cnt_lrc <= cnt_lrc + 1;
            
            rd_en <= 0; 
            if (cnt_lrc == 24 && !fifo_empty) begin
                rd_en <= 1; 
            end

            if (cnt_lrc == 0) begin
                sreg <= fifo_out;
            end else begin
                sreg <= {sreg[14:0], 1'b0}; 
            end
        end else begin
             rd_en <= 0; 
        end
    end

    assign lrc = cnt_lrc[4]; 
    assign din = (cnt_lrc[3:0] == 0) ? 1'b0 : sreg[15];

endmodule

proyecto_I2S/src/fifo/fifo_datapath.v
module fifo_datapath (
    input wire clk, rst,
    input wire [15:0] Dato_In,
    output wire [15:0] Out,
    input wire write_mem,
    input wire inc_wr,
    input wire inc_rd,
    input wire inc_count,
    input wire dec_count,
    output wire count_eq_0,
    output wire count_gt_512
);

    parameter DEPTH = 1024;
    parameter PTR_WIDTH = 10;

    reg [15:0] MEM [0:DEPTH-1];
    reg [15:0] mem_out_reg;

    reg [PTR_WIDTH-1:0] wr_ptr;
    reg [PTR_WIDTH-1:0] rd_ptr;
    reg [PTR_WIDTH:0] count;

    always @(posedge clk) begin
        if (write_mem) begin
            MEM[wr_ptr] <= Dato_In;
        end
        mem_out_reg <= MEM[rd_ptr];
    end

    always @(posedge clk or posedge rst) begin
        if (rst) begin
            wr_ptr <= 0;
            rd_ptr <= 0;
            count  <= 0;
        end else begin
            if (inc_wr) wr_ptr <= wr_ptr + 1;
            if (inc_rd) rd_ptr <= rd_ptr + 1;

            if (inc_count)      count <= count + 1;
            else if (dec_count) count <= count - 1;
        end
    end

    assign Out = mem_out_reg;
    assign count_eq_0   = (count == 0);
    assign count_gt_512 = (count > 512);

endmodule

proyecto_I2S/src/fifo/fifo_control.v
module fifo_control (
    input wire Wr_En,
    input wire Rd_En,
    input wire count_eq_0,
    input wire count_gt_512,
    output reg write_mem,
    output reg inc_wr,
    output reg inc_rd,
    output reg inc_count,
    output reg dec_count,
    output wire Pausa,
    output wire Empty
);

    assign Empty = count_eq_0;
    assign Pausa = count_gt_512;

    always @(*) begin
        write_mem = 0;
        inc_wr    = 0;
        inc_rd    = 0;
        inc_count = 0;
        dec_count = 0;

        if (Wr_En) begin
            write_mem = 1;
            inc_wr    = 1;
        end

        if (Rd_En && !count_eq_0) begin
            inc_rd = 1;
        end

        if (Wr_En && !(Rd_En && !count_eq_0)) begin
            inc_count = 1;
        end
        else if (!Wr_En && (Rd_En && !count_eq_0)) begin
            dec_count = 1;
        end
    end

endmodule

proyecto_I2S/src/fifo/fifo_top.v
module fifo_top (
    input wire clk, rst,
    input wire wr_en,
    input wire rd_en,
    input wire [15:0] dato_in,
    output wire [15:0] out,
    output wire empty,
    output wire pausa
);

    wire w_inc_wr, w_inc_rd, w_write_mem;
    wire w_inc_count, w_dec_count;
    wire w_count_eq_0, w_count_gt_512;

    fifo_control U_CONTROL (
        .Wr_En(wr_en), 
        .Rd_En(rd_en),
        .count_eq_0(w_count_eq_0),
        .count_gt_512(w_count_gt_512),
        .write_mem(w_write_mem),
        .inc_wr(w_inc_wr),
        .inc_rd(w_inc_rd),
        .inc_count(w_inc_count),
        .dec_count(w_dec_count),
        .Pausa(pausa),
        .Empty(empty)
    );

    fifo_datapath U_DATAPATH (
        .clk(clk), 
        .rst(rst),
        .Dato_In(dato_in),
        .Out(out),
        .write_mem(w_write_mem),
        .inc_wr(w_inc_wr),
        .inc_rd(w_inc_rd),
        .inc_count(w_inc_count),
        .dec_count(w_dec_count),
        .count_eq_0(w_count_eq_0),
        .count_gt_512(w_count_gt_512)
    );

endmodule

proyecto_I2S/src/assembler/byte_assembler.v
module byte_assembler (
    input wire clk, rst,
    input wire validar_in,
    input wire [7:0] D,
    output reg we_en,
    output reg [15:0] sample
);

    reg [7:0] temp;
    reg flag;

    always @(posedge clk or posedge rst) begin
        if (rst) begin
            temp <= 0;
            flag <= 0;
            sample <= 0;
            we_en <= 0;
        end else begin
            we_en <= 0;

            if (validar_in) begin
                if (flag == 0) begin
                    temp <= D;
                    flag <= 1;
                end else begin
                    sample <= {D, temp};
                    we_en <= 1;
                    flag <= 0;
                end
            end
        end
    end
endmodule

proyecto_I2S/src/spi/spi_flash_reader.v
module spi_flash_reader (
    input wire clk, rst, start,
    input wire miso,
    input wire pausa,
    input wire [23:0] start_addr,
    
    output reg cs_n,
    output reg mosi,
    output reg sclk,
    output reg validar,
    output reg [7:0] data_out
);

    localparam IDLE = 0;
    localparam SEND_CMD = 1;
    localparam SEND_ADDR = 2;
    localparam READ_LOOP = 3;

    reg [1:0] state;
    reg [4:0] bit_cnt;
    reg [7:0] cmd_reg;
    reg [23:0] addr_reg;
    reg [7:0] shift_reg;

    always @(posedge clk or posedge rst) begin
        if (rst) begin
            state <= IDLE;
            cs_n <= 1; mosi <= 0; sclk <= 0;
            validar <= 0; data_out <= 0;
            bit_cnt <= 0;
        end else begin
            
            if (state == READ_LOOP && pausa) begin
                validar <= 0;
            end 
            else begin
                case (state)
                    IDLE: begin
                        cs_n <= 1;
                        validar <= 0;
                        if (start) begin
                            cs_n <= 0;
                            state <= SEND_CMD;
                            cmd_reg <= 8'h03;
                            bit_cnt <= 7;
                            addr_reg <= start_addr;
                            sclk <= 0;
                        end
                    end

                    SEND_CMD: begin
                        sclk <= ~sclk;
                        if (sclk == 0) begin
                            mosi <= cmd_reg[bit_cnt[2:0]];
                        end else begin
                            if (bit_cnt == 0) begin
                                state <= SEND_ADDR;
                                bit_cnt <= 23;
                            end else begin
                                bit_cnt <= bit_cnt - 1;
                            end
                        end
                    end

                    SEND_ADDR: begin
                        sclk <= ~sclk;
                        if (sclk == 0) begin
                            mosi <= addr_reg[bit_cnt];
                        end else begin
                            if (bit_cnt == 0) begin
                                state <= READ_LOOP;
                                bit_cnt <= 7;
                            end else begin
                                bit_cnt <= bit_cnt - 1;
                            end
                        end
                    end

                    READ_LOOP: begin
                        sclk <= ~sclk;
                        validar <= 0;
                        
                        if (sclk == 0) begin
                             
                        end else begin
                             shift_reg <= {shift_reg[6:0], miso};
                             if (bit_cnt == 0) begin
                                 data_out <= {shift_reg[6:0], miso};
                                 validar <= 1;
                                 bit_cnt <= 7;
                             end else begin
                                 bit_cnt <= bit_cnt - 1;
                             end
                        end
                    end
                endcase
            end
        end
    end
endmodule

proyecto_I2S/src/top.v
module top (
    input wire clk,
    input wire rst_n,
    input wire miso,
    output wire mosi,
    output wire cs_n,
    output wire i2s_bclk,
    output wire i2s_lrc,
    output wire i2s_din,
    output wire led_running
);

    wire rst = ~rst_n;
    
    // Temporizador de arranque (40ms)
    reg [19:0] start_timer;
    reg start_delayed;

    always @(posedge clk) begin
        if (rst) begin
            start_timer <= 0;
            start_delayed <= 0;
        end else begin
            if (start_timer < 20'd1000000) begin
                start_timer <= start_timer + 1;
                start_delayed <= 0;
            end else begin
                start_delayed <= 1;
            end
        end
    end

    wire [23:0] start_addr = 24'h200000; 

    wire [7:0] w_spi_byte;
    wire w_spi_valid;
    wire [15:0] w_asm_sample;
    wire w_asm_we;
    wire w_fifo_pausa;
    wire w_fifo_empty;
    wire [15:0] w_fifo_out;
    wire w_i2s_rd_en;
    wire w_internal_sclk;

    spi_flash_reader U_SPI (
        .clk(clk), 
        .rst(rst), 
        .start(start_delayed),
        .miso(miso), 
        .pausa(w_fifo_pausa),
        .start_addr(start_addr),
        .cs_n(cs_n), 
        .mosi(mosi), 
        .sclk(w_internal_sclk),
        .validar(w_spi_valid), 
        .data_out(w_spi_byte)
    );

    USRMCLK u_mclk (
        .USRMCLKI(w_internal_sclk),
        .USRMCLKTS(1'b0)
    );

    byte_assembler U_ASM (
        .clk(clk), 
        .rst(rst),
        .validar_in(w_spi_valid), 
        .D(w_spi_byte),
        .we_en(w_asm_we), 
        .sample(w_asm_sample)
    );

    fifo_top U_FIFO (
        .clk(clk), 
        .rst(rst),
        .wr_en(w_asm_we), 
        .rd_en(w_i2s_rd_en),
        .dato_in(w_asm_sample),
        .out(w_fifo_out), 
        .empty(w_fifo_empty), 
        .pausa(w_fifo_pausa)
    );

    i2s_tx U_I2S (
        .clk(clk), 
        .rst(rst),
        .fifo_out(w_fifo_out), 
        .fifo_empty(w_fifo_empty),
        .rd_en(w_i2s_rd_en),
        .bclk(i2s_bclk), 
        .din(i2s_din), 
        .lrc(i2s_lrc)
    );

endmodule

proyecto_I2S/sim/top_tb.v
`timescale 1ns / 1ps

module top_tb;

    // Entradas al TOP
    reg clk;
    reg rst_n;
    reg miso;

    // Salidas del TOP
    wire mosi;
    wire cs_n;
    wire i2s_bclk;
    wire i2s_lrc;
    wire i2s_din;
    wire led_running;

    // Instancia del Módulo Principal
    top UUT (
        .clk(clk),
        .rst_n(rst_n),
        .miso(miso),
        .mosi(mosi),
        .cs_n(cs_n),
        .i2s_bclk(i2s_bclk),
        .i2s_lrc(i2s_lrc),
        .i2s_din(i2s_din),
        .led_running(led_running)
    );

    // Generador de Reloj (25 MHz -> 40ns periodo)
    initial begin
        clk = 0;
        forever #20 clk = ~clk;
    end

    // Simulación de la Memoria Flash (Responde 10101010)
    always @(negedge clk) begin
        if (!cs_n) begin
            // Cuando el chip está activo, enviamos datos falsos por MISO
            miso <= $random; 
        end else begin
            miso <= 0;
        end
    end

    // Proceso de Test
    initial begin
        $dumpfile("sim/system_test.vcd");
        $dumpvars(0, top_tb);

        // 1. Inicialización
        rst_n = 0; // Botón presionado (Reset)
        miso = 0;
        #100;
        
        // 2. Soltar Reset
        rst_n = 1; 

        // 3. TRUCO: Saltarnos la espera de 40ms
        // Forzamos el contador interno del TOP para que crea que ya pasó el tiempo
        // Accedemos a la variable interna usando el punto (.)
        force UUT.start_delayed = 1; 
        
        #200;
        // Ahora el timer debería desbordar y activar start_delayed
        
        // 4. Dejar correr para ver SPI e I2S
        #50000; // Correr suficiente tiempo para ver tramas I2S

        $finish;
    end

endmodule
module USRMCLK (
    input USRMCLKI,
    input USRMCLKTS
);
endmodule

proyecto_I2S/sim/system_test.vcd
$date
	Tue Dec  9 02:03:57 2025
$end
$version
	Icarus Verilog
$end
$timescale
	1ps
$end
$scope module top_tb $end
$var wire 1 ! led_running $end
$var wire 1 " mosi $end
$var wire 1 # i2s_lrc $end
$var wire 1 $ i2s_din $end
$var wire 1 % i2s_bclk $end
$var wire 1 & cs_n $end
$var reg 1 ' clk $end
$var reg 1 ( miso $end
$var reg 1 ) rst_n $end
$scope module UUT $end
$var wire 1 ' clk $end
$var wire 1 ! led_running $end
$var wire 1 ( miso $end
$var wire 1 * rst $end
$var wire 1 ) rst_n $end
$var wire 24 + start_addr [23:0] $end
$var wire 1 , w_spi_valid $end
$var wire 8 - w_spi_byte [7:0] $end
$var wire 1 . w_internal_sclk $end
$var wire 1 / w_i2s_rd_en $end
$var wire 1 0 w_fifo_pausa $end
$var wire 16 1 w_fifo_out [15:0] $end
$var wire 1 2 w_fifo_empty $end
$var wire 1 3 w_asm_we $end
$var wire 16 4 w_asm_sample [15:0] $end
$var wire 1 " mosi $end
$var wire 1 # i2s_lrc $end
$var wire 1 $ i2s_din $end
$var wire 1 % i2s_bclk $end
$var wire 1 & cs_n $end
$var reg 1 5 start_delayed $end
$var reg 20 6 start_timer [19:0] $end
$scope module U_ASM $end
$var wire 1 ' clk $end
$var wire 1 * rst $end
$var wire 1 , validar_in $end
$var wire 8 7 D [7:0] $end
$var reg 1 8 flag $end
$var reg 16 9 sample [15:0] $end
$var reg 8 : temp [7:0] $end
$var reg 1 3 we_en $end
$upscope $end
$scope module U_FIFO $end
$var wire 1 ' clk $end
$var wire 16 ; dato_in [15:0] $end
$var wire 1 * rst $end
$var wire 1 3 wr_en $end
$var wire 1 < w_write_mem $end
$var wire 1 = w_inc_wr $end
$var wire 1 > w_inc_rd $end
$var wire 1 ? w_inc_count $end
$var wire 1 @ w_dec_count $end
$var wire 1 A w_count_gt_512 $end
$var wire 1 B w_count_eq_0 $end
$var wire 1 / rd_en $end
$var wire 1 0 pausa $end
$var wire 16 C out [15:0] $end
$var wire 1 2 empty $end
$scope module U_CONTROL $end
$var wire 1 2 Empty $end
$var wire 1 0 Pausa $end
$var wire 1 3 Wr_En $end
$var wire 1 A count_gt_512 $end
$var wire 1 B count_eq_0 $end
$var wire 1 / Rd_En $end
$var reg 1 @ dec_count $end
$var reg 1 ? inc_count $end
$var reg 1 > inc_rd $end
$var reg 1 = inc_wr $end
$var reg 1 < write_mem $end
$upscope $end
$scope module U_DATAPATH $end
$var wire 16 D Dato_In [15:0] $end
$var wire 16 E Out [15:0] $end
$var wire 1 ' clk $end
$var wire 1 @ dec_count $end
$var wire 1 ? inc_count $end
$var wire 1 > inc_rd $end
$var wire 1 = inc_wr $end
$var wire 1 * rst $end
$var wire 1 < write_mem $end
$var wire 1 A count_gt_512 $end
$var wire 1 B count_eq_0 $end
$var parameter 32 F DEPTH $end
$var parameter 32 G PTR_WIDTH $end
$var reg 11 H count [10:0] $end
$var reg 16 I mem_out_reg [15:0] $end
$var reg 10 J rd_ptr [9:0] $end
$var reg 10 K wr_ptr [9:0] $end
$upscope $end
$upscope $end
$scope module U_I2S $end
$var wire 1 ' clk $end
$var wire 1 2 fifo_empty $end
$var wire 16 L fifo_out [15:0] $end
$var wire 1 * rst $end
$var wire 1 # lrc $end
$var wire 1 $ din $end
$var parameter 32 M LIMIT $end
$var reg 1 % bclk $end
$var reg 5 N cnt_lrc [4:0] $end
$var reg 1 / rd_en $end
$var reg 16 O sreg [15:0] $end
$var reg 1 P strobe $end
$var reg 8 Q tick [7:0] $end
$upscope $end
$scope module U_SPI $end
$var wire 1 ' clk $end
$var wire 1 ( miso $end
$var wire 1 0 pausa $end
$var wire 1 * rst $end
$var wire 1 5 start $end
$var wire 24 R start_addr [23:0] $end
$var parameter 32 S IDLE $end
$var parameter 32 T READ_LOOP $end
$var parameter 32 U SEND_ADDR $end
$var parameter 32 V SEND_CMD $end
$var reg 24 W addr_reg [23:0] $end
$var reg 5 X bit_cnt [4:0] $end
$var reg 8 Y cmd_reg [7:0] $end
$var reg 1 & cs_n $end
$var reg 8 Z data_out [7:0] $end
$var reg 1 " mosi $end
$var reg 1 . sclk $end
$var reg 8 [ shift_reg [7:0] $end
$var reg 2 \ state [1:0] $end
$var reg 1 , validar $end
$upscope $end
$scope module u_mclk $end
$var wire 1 . USRMCLKI $end
$var wire 1 ] USRMCLKTS $end
$upscope $end
$upscope $end
$upscope $end
$enddefinitions $end
$comment Show the parameter values. $end
$dumpall
b1 V
b10 U
b11 T
b0 S
b10010 M
b1010 G
b10000000000 F
$end
#0
$dumpvars
0]
b0 \
bx [
b0 Z
bx Y
b0 X
bx W
b1000000000000000000000 R
bx Q
xP
bx O
bx N
bx L
b0 K
b0 J
bx I
b0 H
bx E
b0 D
bx C
1B
0A
0@
0?
0>
0=
0<
b0 ;
b0 :
b0 9
08
b0 7
bx 6
x5
b0 4
03
12
bx 1
00
x/
0.
b0 -
0,
b1000000000000000000000 +
1*
0)
0(
0'
1&
x%
x$
x#
0"
z!
$end
#20000
0$
0#
0P
0%
b0 Q
b0 O
0/
b0 N
05
b0 6
1'
#40000
0'
#60000
1'
#80000
0'
#100000
b1000000000000000000000 W
b111 X
b11 Y
b1 \
0&
b1 Q
b1 6
0*
1'
15
1)
#120000
0'
#140000
1.
b10 6
b10 Q
1'
#160000
1(
0'
#180000
b110 X
0.
b11 Q
b11 6
1'
#200000
0'
#220000
1.
b100 6
b100 Q
1'
#240000
0'
#260000
b101 X
0.
b101 Q
b101 6
1'
#280000
0'
#300000
1.
b110 6
b110 Q
1'
#320000
0'
#340000
b100 X
0.
b111 Q
b111 6
1'
#360000
0'
#380000
1.
b1000 6
b1000 Q
1'
#400000
0(
0'
#420000
b11 X
0.
b1001 Q
b1001 6
1'
#440000
1(
0'
#460000
1.
b1010 6
b1010 Q
1'
#480000
0'
#500000
b10 X
0.
b1011 Q
b1011 6
1'
#520000
0(
0'
#540000
1.
b1100 6
b1100 Q
1'
#560000
1(
0'
#580000
b1 X
0.
b1101 Q
b1101 6
1'
#600000
0'
#620000
1"
1.
b1110 6
b1110 Q
1'
#640000
0(
0'
#660000
b0 X
0.
b1111 Q
b1111 6
1'
#680000
1(
0'
#700000
1.
b10000 6
b10000 Q
1'
#720000
0(
0'
#740000
b10111 X
b10 \
0.
b10001 Q
b10001 6
1'
#760000
1(
0'
#780000
0"
1.
b10010 6
1%
b0 Q
1'
#800000
0(
0'
#820000
b10110 X
0.
b1 Q
b10011 6
1'
#840000
1(
0'
#860000
1.
b10100 6
b10 Q
1'
#880000
0'
#900000
b10101 X
0.
b11 Q
b10101 6
1'
#920000
0(
0'
#940000
1"
1.
b10110 6
b100 Q
1'
#960000
1(
0'
#980000
b10100 X
0.
b101 Q
b10111 6
1'
#1000000
0(
0'
#1020000
0"
1.
b11000 6
b110 Q
1'
#1040000
0'
#1060000
b10011 X
0.
b111 Q
b11001 6
1'
#1080000
0'
#1100000
1.
b11010 6
b1000 Q
1'
#1120000
1(
0'
#1140000
b10010 X
0.
b1001 Q
b11011 6
1'
#1160000
0(
0'
#1180000
1.
b11100 6
b1010 Q
1'
#1200000
1(
0'
#1220000
b10001 X
0.
b1011 Q
b11101 6
1'
#1240000
0'
#1260000
1.
b11110 6
b1100 Q
1'
#1280000
0'
#1300000
b10000 X
0.
b1101 Q
b11111 6
1'
#1320000
0'
#1340000
1.
b100000 6
b1110 Q
1'
#1360000
0(
0'
#1380000
b1111 X
0.
b1111 Q
b100001 6
1'
#1400000
0'
#1420000
1.
b100010 6
b10000 Q
1'
#1440000
0'
#1460000
b1110 X
0.
b10001 Q
b100011 6
1'
#1480000
0'
#1500000
1.
b100100 6
1P
0%
b0 Q
1'
#1520000
1(
0'
#1540000
x$
b1101 X
0.
b1 Q
0P
bx O
b1 N
b100101 6
1'
#1560000
0(
0'
#1580000
1.
b100110 6
b10 Q
1'
#1600000
1(
0'
#1620000
b1100 X
0.
b11 Q
b100111 6
1'
#1640000
0'
#1660000
1.
b101000 6
b100 Q
1'
#1680000
0'
#1700000
b1011 X
0.
b101 Q
b101001 6
1'
#1720000
0'
#1740000
1.
b101010 6
b110 Q
1'
#1760000
0'
#1780000
b1010 X
0.
b111 Q
b101011 6
1'
#1800000
0(
0'
#1820000
1.
b101100 6
b1000 Q
1'
#1840000
0'
#1860000
b1001 X
0.
b1001 Q
b101101 6
1'
#1880000
1(
0'
#1900000
1.
b101110 6
b1010 Q
1'
#1920000
0'
#1940000
b1000 X
0.
b1011 Q
b101111 6
1'
#1960000
0'
#1980000
1.
b110000 6
b1100 Q
1'
#2000000
0(
0'
#2020000
b111 X
0.
b1101 Q
b110001 6
1'
#2040000
0'
#2060000
1.
b110010 6
b1110 Q
1'
#2080000
0'
#2100000
b110 X
0.
b1111 Q
b110011 6
1'
#2120000
0'
#2140000
1.
b110100 6
b10000 Q
1'
#2160000
0'
#2180000
b101 X
0.
b10001 Q
b110101 6
1'
#2200000
1(
0'
#2220000
1.
b110110 6
1%
b0 Q
1'
#2240000
0(
0'
#2260000
b100 X
0.
b1 Q
b110111 6
1'
#2280000
0'
#2300000
1.
b111000 6
b10 Q
1'
#2320000
1(
0'
#2340000
b11 X
0.
b11 Q
b111001 6
1'
#2360000
0'
#2380000
1.
b111010 6
b100 Q
1'
#2400000
0(
0'
#2420000
b10 X
0.
b101 Q
b111011 6
1'
#2440000
0'
#2460000
1.
b111100 6
b110 Q
1'
#2480000
0'
#2500000
b1 X
0.
b111 Q
b111101 6
1'
#2520000
0'
#2540000
1.
b111110 6
b1000 Q
1'
#2560000
0'
#2580000
b0 X
0.
b1001 Q
b111111 6
1'
#2600000
1(
0'
#2620000
1.
b1000000 6
b1010 Q
1'
#2640000
0'
#2660000
b111 X
b11 \
0.
b1011 Q
b1000001 6
1'
#2680000
0'
#2700000
1.
b1000010 6
b1100 Q
1'
#2720000
0'
#2740000
b110 X
bx1 [
0.
b1101 Q
b1000011 6
1'
#2760000
0'
#2780000
1.
b1000100 6
b1110 Q
1'
#2800000
0(
0'
#2820000
b101 X
bx10 [
0.
b1111 Q
b1000101 6
1'
#2840000
0'
#2860000
1.
b1000110 6
b10000 Q
1'
#2880000
1(
0'
#2900000
b100 X
bx101 [
0.
b10001 Q
b1000111 6
1'
#2920000
0'
#2940000
1.
b1001000 6
1P
0%
b0 Q
1'
#2960000
0'
#2980000
b11 X
bx1011 [
0.
b1 Q
0P
bx0 O
b10 N
b1001001 6
1'
#3000000
0(
0'
#3020000
1.
b1001010 6
b10 Q
1'
#3040000
0'
#3060000
b10 X
bx10110 [
0.
b11 Q
b1001011 6
1'
#3080000
1(
0'
#3100000
1.
b1001100 6
b100 Q
1'
#3120000
0'
#3140000
b1 X
bx101101 [
0.
b101 Q
b1001101 6
1'
#3160000
0(
0'
#3180000
1.
b1001110 6
b110 Q
1'
#3200000
1(
0'
#3220000
b0 X
bx1011011 [
0.
b111 Q
b1001111 6
1'
#3240000
0'
#3260000
1.
b1010000 6
b1000 Q
1'
#3280000
0(
0'
#3300000
b111 X
1,
b10110110 -
b10110110 7
b10110110 Z
b10110110 [
0.
b1001 Q
b1010001 6
1'
#3320000
1(
0'
#3340000
0,
1.
18
b10110110 :
b1010010 6
b1010 Q
1'
#3360000
0'
#3380000
b110 X
b1101101 [
0.
b1011 Q
b1010011 6
1'
#3400000
0'
#3420000
1.
b1010100 6
b1100 Q
1'
#3440000
0(
0'
#3460000
b101 X
b11011010 [
0.
b1101 Q
b1010101 6
1'
#3480000
1(
0'
#3500000
1.
b1010110 6
b1110 Q
1'
#3520000
0'
#3540000
b100 X
b10110101 [
0.
b1111 Q
b1010111 6
1'
#3560000
0(
0'
#3580000
1.
b1011000 6
b10000 Q
1'
#3600000
0'
#3620000
b11 X
b1101010 [
0.
b10001 Q
b1011001 6
1'
#3640000
0'
#3660000
1.
b1011010 6
1%
b0 Q
1'
#3680000
0'
#3700000
b10 X
b11010100 [
0.
b1 Q
b1011011 6
1'
#3720000
1(
0'
#3740000
1.
b1011100 6
b10 Q
1'
#3760000
0'
#3780000
b1 X
b10101001 [
0.
b11 Q
b1011101 6
1'
#3800000
0(
0'
#3820000
1.
b1011110 6
b100 Q
1'
#3840000
0'
#3860000
b0 X
b1010010 [
0.
b101 Q
b1011111 6
1'
#3880000
1(
0'
#3900000
1.
b1100000 6
b110 Q
1'
#3920000
0'
#3940000
b111 X
1,
b10100101 -
b10100101 7
b10100101 Z
b10100101 [
0.
b111 Q
b1100001 6
1'
#3960000
0'
#3980000
1?
1=
1<
0,
1.
08
13
b1010010110110110 4
b1010010110110110 9
b1010010110110110 ;
b1010010110110110 D
b1100010 6
b1000 Q
1'
#4000000
0'
#4020000
0?
0=
0<
02
0B
b1 H
b1 K
03
b110 X
b1001011 [
0.
b1001 Q
b1100011 6
1'
#4040000
0'
#4060000
1.
b1100100 6
b1010 Q
b1010010110110110 1
b1010010110110110 C
b1010010110110110 E
b1010010110110110 L
b1010010110110110 I
1'
#4080000
0(
0'
#4100000
b101 X
b10010110 [
0.
b1011 Q
b1100101 6
1'
#4120000
1(
0'
#4140000
1.
b1100110 6
b1100 Q
1'
#4160000
0'
#4180000
b100 X
b101101 [
0.
b1101 Q
b1100111 6
1'
#4200000
0'
#4220000
1.
b1101000 6
b1110 Q
1'
#4240000
0(
0'
#4260000
b11 X
b1011010 [
0.
b1111 Q
b1101001 6
1'
#4280000
0'
#4300000
1.
b1101010 6
b10000 Q
1'
#4320000
0'
#4340000
b10 X
b10110100 [
0.
b10001 Q
b1101011 6
1'
#4360000
0'
#4380000
1.
b1101100 6
1P
0%
b0 Q
1'
#4400000
0'
#4420000
b1 X
b1101000 [
0.
b1 Q
0P
bx00 O
b11 N
b1101101 6
1'
#4440000
0'
#4460000
1.
b1101110 6
b10 Q
1'
#4480000
0'
#4500000
b0 X
b11010000 [
0.
b11 Q
b1101111 6
1'
#4520000
1(
0'
#4540000
1.
b1110000 6
b100 Q
1'
#4560000
0'
#4580000
b111 X
1,
b10100001 -
b10100001 7
b10100001 Z
b10100001 [
0.
b101 Q
b1110001 6
1'
#4600000
0'
#4620000
0,
1.
18
b10100001 :
b1110010 6
b110 Q
1'
#4640000
0'
#4660000
b110 X
b1000011 [
0.
b111 Q
b1110011 6
1'
#4680000
0'
#4700000
1.
b1110100 6
b1000 Q
1'
#4720000
0(
0'
#4740000
b101 X
b10000110 [
0.
b1001 Q
b1110101 6
1'
#4760000
1(
0'
#4780000
1.
b1110110 6
b1010 Q
1'
#4800000
0'
#4820000
b100 X
b1101 [
0.
b1011 Q
b1110111 6
1'
#4840000
0(
0'
#4860000
1.
b1111000 6
b1100 Q
1'
#4880000
0'
#4900000
b11 X
b11010 [
0.
b1101 Q
b1111001 6
1'
#4920000
1(
0'
#4940000
1.
b1111010 6
b1110 Q
1'
#4960000
0'
#4980000
b10 X
b110101 [
0.
b1111 Q
b1111011 6
1'
#5000000
0(
0'
#5020000
1.
b1111100 6
b10000 Q
1'
#5040000
1(
0'
#5060000
b1 X
b1101011 [
0.
b10001 Q
b1111101 6
1'
#5080000
0'
#5100000
1.
b1111110 6
1%
b0 Q
1'
#5120000
0'
#5140000
b0 X
b11010111 [
0.
b1 Q
b1111111 6
1'
#5160000
0'
#5180000
1.
b10000000 6
b10 Q
1'
#5200000
0(
0'
#5220000
b111 X
1,
b10101110 -
b10101110 7
b10101110 Z
b10101110 [
0.
b11 Q
b10000001 6
1'
#5240000
0'
#5260000
1?
1=
1<
0,
1.
08
13
b1010111010100001 4
b1010111010100001 9
b1010111010100001 ;
b1010111010100001 D
b10000010 6
b100 Q
1'
#5280000
0'
#5300000
0?
0=
0<
b10 H
b10 K
03
b110 X
b1011100 [
0.
b101 Q
b10000011 6
1'
#5320000
1(
0'
#5340000
1.
b10000100 6
b110 Q
1'
#5360000
0(
0'
#5380000
b101 X
b10111000 [
0.
b111 Q
b10000101 6
1'
#5400000
0'
#5420000
1.
b10000110 6
b1000 Q
1'
#5440000
0'
#5460000
b100 X
b1110000 [
0.
b1001 Q
b10000111 6
1'
#5480000
1(
0'
#5500000
1.
b10001000 6
b1010 Q
1'
#5520000
0'
#5540000
b11 X
b11100001 [
0.
b1011 Q
b10001001 6
1'
#5560000
0(
0'
#5580000
1.
b10001010 6
b1100 Q
1'
#5600000
0'
#5620000
b10 X
b11000010 [
0.
b1101 Q
b10001011 6
1'
#5640000
1(
0'
#5660000
1.
b10001100 6
b1110 Q
1'
#5680000
0(
0'
#5700000
b1 X
b10000100 [
0.
b1111 Q
b10001101 6
1'
#5720000
0'
#5740000
1.
b10001110 6
b10000 Q
1'
#5760000
0'
#5780000
b0 X
b1000 [
0.
b10001 Q
b10001111 6
1'
#5800000
1(
0'
#5820000
1.
b10010000 6
1P
0%
b0 Q
1'
#5840000
0(
0'
#5860000
b111 X
1,
b10000 -
b10000 7
b10000 Z
b10000 [
0.
b1 Q
0P
bx000 O
b100 N
b10010001 6
1'
#5880000
0'
#5900000
0,
1.
18
b10000 :
b10010010 6
b10 Q
1'
#5920000
1(
0'
#5940000
b110 X
b100001 [
0.
b11 Q
b10010011 6
1'
#5960000
0(
0'
#5980000
1.
b10010100 6
b100 Q
1'
#6000000
1(
0'
#6020000
b101 X
b1000011 [
0.
b101 Q
b10010101 6
1'
#6040000
0'
#6060000
1.
b10010110 6
b110 Q
1'
#6080000
0'
#6100000
b100 X
b10000111 [
0.
b111 Q
b10010111 6
1'
#6120000
0'
#6140000
1.
b10011000 6
b1000 Q
1'
#6160000
0'
#6180000
b11 X
b1111 [
0.
b1001 Q
b10011001 6
1'
#6200000
0(
0'
#6220000
1.
b10011010 6
b1010 Q
1'
#6240000
0'
#6260000
b10 X
b11110 [
0.
b1011 Q
b10011011 6
1'
#6280000
0'
#6300000
1.
b10011100 6
b1100 Q
1'
#6320000
1(
0'
#6340000
b1 X
b111101 [
0.
b1101 Q
b10011101 6
1'
#6360000
0(
0'
#6380000
1.
b10011110 6
b1110 Q
1'
#6400000
0'
#6420000
b0 X
b1111010 [
0.
b1111 Q
b10011111 6
1'
#6440000
1(
0'
#6460000
1.
b10100000 6
b10000 Q
1'
#6480000
0'
#6500000
b111 X
1,
b11110101 -
b11110101 7
b11110101 Z
b11110101 [
0.
b10001 Q
b10100001 6
1'
#6520000
0(
0'
#6540000
1?
1=
1<
0,
1.
08
13
b1111010100010000 4
b1111010100010000 9
b1111010100010000 ;
b1111010100010000 D
b10100010 6
1%
b0 Q
1'
#6560000
0'
#6580000
0?
0=
0<
b11 H
b11 K
03
b110 X
b11101010 [
0.
b1 Q
b10100011 6
1'
#6600000
0'
#6620000
1.
b10100100 6
b10 Q
1'
#6640000
1(
0'
#6660000
b101 X
b11010101 [
0.
b11 Q
b10100101 6
1'
#6680000
0'
#6700000
1.
b10100110 6
b100 Q
1'
#6720000
0(
0'
#6740000
b100 X
b10101010 [
0.
b101 Q
b10100111 6
1'
#6760000
0'
#6780000
1.
b10101000 6
b110 Q
1'
#6800000
0'
