src/div.v
module division_entera #(
parameter N = 8
)(
input wire clk,
input wire rst,
input wire start,
input wire [N-1:0] A,
input wire [N-1:0] B,
output reg [N-1:0] Q,
output reg [N-1:0] R,
output reg done
);
reg [N-1:0] B_reg;
reg [2*N-1:0] A_ext;
reg [N-1:0] count;
reg [1:0] state;
localparam IDLE = 2'b00;
localparam CALC = 2'b01;
localparam DONE = 2'b10;
wire [2*N-1:0] shifted_A = {A_ext[2*N-2:0], 1'b0};
wire [N-1:0] upper_part = shifted_A[2*N-1:N];
wire cabe = (upper_part >= B_reg);
wire [N-1:0] diff = upper_part - B_reg;
wire [2*N-1:0] next_A_val;
assign next_A_val = cabe ? {diff, shifted_A[N-1:1], 1'b1} : shifted_A;
always @(posedge clk or posedge rst) begin
if (rst) begin
state <= IDLE;
done <= 0;
Q <= 0;
R <= 0;
count <= 0;
A_ext <= 0;
B_reg <= 0;
end else begin
case (state)
IDLE: begin
done <= 0;
if (start) begin
B_reg <= B;
count <= N;
A_ext <= {{N{1'b0}}, A};
state <= CALC;
end
end
CALC: begin
A_ext <= next_A_val;
count <= count - 1;
if (count == 1) begin
state <= DONE;
end
end
DONE: begin
done <= 1;
Q <= A_ext[N-1:0];
R <= A_ext[2*N-1:N];
if (!start) begin
state <= IDLE;
end
end
endcase
end
end
endmodule

CalculadoraFPGA/sim/div_tb.v
`timescale 1ns / 1ps

module tb_division_entera;

    parameter N = 8;

    reg clk;
    reg rst;
    reg start;
    reg [N-1:0] A;
    reg [N-1:0] B;
    wire [N-1:0] Q;
    wire [N-1:0] R;
    wire done;

    division_entera #(.N(N)) dut (
        .clk(clk),
        .rst(rst),
        .start(start),
        .A(A),
        .B(B),
        .Q(Q),
        .R(R),
        .done(done)
    );

    // Reloj
    initial begin
        clk = 0;
        forever #5 clk = ~clk;
    end

    initial begin
        #2000;
        $display("ERROR CRÍTICO: La simulación se colgó (Timeout).");
        $display("Revisa si el contador está bajando o si entraste al estado CALC.");
        $finish;
    end

    initial begin
        $monitor("Tiempo: %t | Estado: %d | Count: %d | A_ext: %b | Done: %b", 
                 $time, dut.state, dut.count, dut.A_ext, done);
    end

    // Pruebas
    initial begin
        $dumpfile("division.vcd");
        $dumpvars(0, tb_division_entera);

        // Reset
        rst = 1; start = 0; A = 0; B = 0;
        #20;
        rst = 0;
        #20;

        // Prueba: 15 / 4
        $display("--- Iniciando Prueba 15/4 ---");
        A = 8'd15;
        B = 8'd4;
        start = 1; 
        #10; // Pulso de start
        start = 0;

        // Esperamos (pero el Timeout nos salvará si falla)
        wait(done);
        
        $display(">>> ÉXITO: Resultado 15/4 -> Q: %d, R: %d", Q, R);
        $finish;
    end

endmodule

CalculadoraFPGA/division.vcd
$date
	Mon Nov 24 06:46:26 2025
$end
$version
	Icarus Verilog
$end
$timescale
	1ps
$end
$scope module tb_division_entera $end
$var wire 1 ! done $end
$var wire 8 " R [7:0] $end
$var wire 8 # Q [7:0] $end
$var parameter 32 $ N $end
$var reg 8 % A [7:0] $end
$var reg 8 & B [7:0] $end
$var reg 1 ' clk $end
$var reg 1 ( rst $end
$var reg 1 ) start $end
$scope module dut $end
$var wire 8 * A [7:0] $end
$var wire 8 + B [7:0] $end
$var wire 1 ' clk $end
$var wire 1 ( rst $end
$var wire 1 ) start $end
$var wire 8 , upper_part [7:0] $end
$var wire 16 - shifted_A [15:0] $end
$var wire 16 . next_A_val [15:0] $end
$var wire 8 / diff [7:0] $end
$var wire 1 0 cabe $end
$var parameter 2 1 CALC $end
$var parameter 2 2 DONE $end
$var parameter 2 3 IDLE $end
$var parameter 32 4 N $end
$var reg 16 5 A_ext [15:0] $end
$var reg 8 6 B_reg [7:0] $end
$var reg 8 7 Q [7:0] $end
$var reg 8 8 R [7:0] $end
$var reg 8 9 count [7:0] $end
$var reg 1 ! done $end
$var reg 2 : state [1:0] $end
$upscope $end
$upscope $end
$enddefinitions $end
$comment Show the parameter values. $end
$dumpall
b1000 4
b0 3
b10 2
b1 1
b1000 $
$end
#0
$dumpvars
b0 :
b0 9
b0 8
b0 7
b0 6
b0 5
10
b0 /
b1 .
b0 -
b0 ,
b0 +
b0 *
0)
1(
0'
b0 &
b0 %
b0 #
b0 "
0!
$end
#5000
1'
#10000
0'
#15000
1'
#20000
0'
0(
#25000
1'
#30000
0'
#35000
1'
#40000
0'
1)
b100 &
b100 +
b1111 %
b1111 *
#45000
b11110 -
b11110 .
b1 :
b1111 5
b1000 9
00
b11111100 /
b100 6
1'
#50000
0'
0)
#55000
b111100 .
b111100 -
b111 9
b11110 5
1'
#60000
0'
#65000
b1111000 .
b1111000 -
b110 9
b111100 5
1'
#70000
0'
#75000
b11110000 .
b11110000 -
b101 9
b1111000 5
1'
#80000
0'
#85000
b11111101 /
b1 ,
b111100000 .
b111100000 -
b100 9
b11110000 5
1'
#90000
0'
#95000
b11111111 /
b11 ,
b1111000000 .
b1111000000 -
b11 9
b111100000 5
1'
#100000
0'
#105000
10
b11 /
b111 ,
b1110000001 .
b11110000000 -
b10 9
b1111000000 5
1'
#110000
0'
#115000
b1100000011 .
b11100000010 -
b1 9
b1110000001 5
1'
#120000
0'
#125000
b1000000111 .
b10 /
b110 ,
b11000000110 -
b10 :
b0 9
b1100000011 5
1'
#130000
0'
#135000
b0 :
b11 "
b11 8
b11 #
b11 7
1!
1'
